mawo_natasha/__init__.py
mawo_natasha/const.py
mawo_natasha/extractors.py
mawo_natasha/fact.py
mawo_natasha/markup.py
mawo_natasha/model_cache_manager.py
mawo_natasha/morph_vocab.py
mawo_natasha/navec_integration.py
mawo_natasha/norm.py
mawo_natasha/segmenter.py
mawo_natasha/span.py
mawo_natasha-1.0.3.dist-info/licenses/LICENSE
mawo_natasha-1.0.3.dist-info/METADATA
mawo_natasha-1.0.3.dist-info/WHEEL
mawo_natasha-1.0.3.dist-info/top_level.txt
mawo_natasha-1.0.3.dist-info/RECORD
