Metadata-Version: 2.4
Name: mawo-natasha
Version: 1.0.3
Summary: NER и семантический анализ для русского языка с Navec embeddings
Author-email: MAWO Team <team@mawo.ru>
Maintainer-email: MAWO Team <team@mawo.ru>
License: MIT
Project-URL: Homepage, https://github.com/mawo-ru/mawo-natasha
Project-URL: Documentation, https://github.com/mawo-ru/mawo-natasha#readme
Project-URL: Repository, https://github.com/mawo-ru/mawo-natasha
Project-URL: Issues, https://github.com/mawo-ru/mawo-natasha/issues
Project-URL: Changelog, https://github.com/mawo-ru/mawo-natasha/blob/main/CHANGELOG.md
Keywords: nlp,russian,ner,natasha,navec,embeddings,mawo
Classifier: Development Status :: 5 - Production/Stable
Classifier: Intended Audience :: Developers
Classifier: Intended Audience :: Science/Research
Classifier: License :: OSI Approved :: MIT License
Classifier: Natural Language :: Russian
Classifier: Operating System :: OS Independent
Classifier: Programming Language :: Python :: 3
Classifier: Programming Language :: Python :: 3.10
Classifier: Programming Language :: Python :: 3.11
Classifier: Programming Language :: Python :: 3.12
Classifier: Programming Language :: Python :: 3.13
Classifier: Topic :: Scientific/Engineering :: Artificial Intelligence
Classifier: Topic :: Text Processing :: Linguistic
Requires-Python: >=3.10
License-File: LICENSE
Requires-Dist: numpy>=1.20.0
Provides-Extra: dev
Requires-Dist: pytest>=7.0; extra == "dev"
Requires-Dist: pytest-cov>=4.0; extra == "dev"
Requires-Dist: black>=23.0; extra == "dev"
Requires-Dist: ruff>=0.1.0; extra == "dev"
Requires-Dist: mypy>=1.0; extra == "dev"
Provides-Extra: slovnet
Requires-Dist: mawo-slovnet>=1.0.0; extra == "slovnet"
Provides-Extra: all
Requires-Dist: mawo-natasha[dev,slovnet]; extra == "all"
Dynamic: license-file
